gnome_pomodoro_tracking/__init__.py
gnome_pomodoro_tracking/__main__.py
gnome_pomodoro_tracking/clockify.py
gnome_pomodoro_tracking/odoo.py
gnome_pomodoro_tracking/plugin.py
gnome_pomodoro_tracking/toggl.py
gnome_pomodoro_tracking/tracking.py
gnome_pomodoro_tracking/utils.py
gnome_pomodoro_tracking-4.1.2.dist-info/LICENSE
gnome_pomodoro_tracking-4.1.2.dist-info/METADATA
gnome_pomodoro_tracking-4.1.2.dist-info/WHEEL
gnome_pomodoro_tracking-4.1.2.dist-info/entry_points.txt
gnome_pomodoro_tracking-4.1.2.dist-info/top_level.txt
gnome_pomodoro_tracking-4.1.2.dist-info/RECORD
