Metadata-Version: 2.1
Name: gnome-pomodoro-tracking
Version: 4.1.2
Summary: Connect your Pomodoros to popular time tracking services.
Home-page: https://github.com/gnome-pomodoro/gnome-pomodoro-tracking
Author: Jose Hbez
Author-email: josehbez@outlook.com
License: MIT
Classifier: Environment :: Console
Classifier: Intended Audience :: End Users/Desktop
Classifier: Intended Audience :: Developers
Classifier: License :: OSI Approved :: MIT License
Classifier: Operating System :: POSIX :: Linux
Classifier: Programming Language :: Python :: 3 :: Only
Classifier: Programming Language :: Python :: 3
Classifier: Topic :: Utilities
License-File: LICENSE
Requires-Dist: requests
